Workbook
Name aporte: Planilha1!$E$11:$E$11
Name patrimonio: Planilha1!$E$14:$E$14
Name qtd_anos: Planilha1!$E$12:$E$12
Name rendimento_carteira: Planilha1!$E$7:$E$7
Name salario: Planilha1!$E$6:$E$6
Name sugestao_investimento: Planilha1!$E$8:$E$8
Name taxa_mensal: Planilha1!$E$13:$E$13

Sheet Planilha1
A1: PLANO DE INVESTIMENTO | B1: G.F. INVEST
B5: CONFIGURAÇÕES
B6: Salário | E6: 4200
B7: Rendimento da Carteira | E7: 0.01
B8: Sugestão de Investimento (30%) | E8: {=(salario*30%)} -> 1260
B10: INVESTIMENTO MENSAL
B11: Quanto investir por mês? | E11: 1260
B12: Por quantos anos? | E12: 10
B13: Taxa de Rendimento Mensal | E13: 0.01079
B14: Patrimônio acumulado | E14: {=FV(taxa_mensal,qtd_anos*12,aporte)*-1} -> 306538.11
B15: Dividendos mensais | E15: {=(patrimonio*rendimento_carteira)} -> 3065.3811
A17: 2 | B17: CENÁRIOS | E17: Dividendos
A18: 5 | B18: Quanto em 2 anos? | C18: =FV($E$13,$A17*12,$E$11)*-1 -> 34306.81 | E18: {=(C18*rendimento_carteira)} -> 343.0681
A19: 10 | B19: Quanto em 5 anos? | C19: =FV($E$13,$A18*12,$E$11)*-1 -> 105558.91 | E19: {=(C19*rendimento_carteira)} -> 1055.5891
A20: 20 | B20: Quanto em 10 anos? | C20: =FV($E$13,$A19*12,$E$11)*-1 -> 306538.11 | E20: {=(C20*rendimento_carteira)} -> 3065.3811
A21: 30 | B21: Quanto em 20 anos? | C21: =FV($E$13,$A20*12,$E$11)*-1 -> 1417750 | E21: {=(C21*rendimento_carteira)} -> 14177.5
B22: Quanto em 30 anos? | C22: =FV($E$13,$A21*12,$E$11)*-1 -> 5445933.8 | E22: {=(C22*rendimento_carteira)} -> 54459.338
B25: PERFIL | E25: Agressivo
B26: Valor a ser investido por mês | C26: {=aporte} -> 1260
B28: TIPOS DE FI | C28: % Sugerido | E28: Valores
B29: PAPEL | C29: =VLOOKUP($E$25&"-"&B29,Planilha2!$A:$D,4,FALSE) -> 0.5 | E29: =($C$26*C29) -> 630
B30: TIJOLO | C30: =VLOOKUP($E$25&"-"&B30,Planilha2!$A:$D,4,FALSE) -> 0.1 | E30: =($C$26*C30) -> 126
B31: HÍBRIDOS | C31: =VLOOKUP($E$25&"-"&B31,Planilha2!$A:$D,4,FALSE) -> 0.05 | E31: =($C$26*C31) -> 63
B32: FOFs | C32: =VLOOKUP($E$25&"-"&B32,Planilha2!$A:$D,4,FALSE) -> 0.1 | E32: =($C$26*C32) -> 126
B33: DESENVOLVIMENTO | C33: =VLOOKUP($E$25&"-"&B33,Planilha2!$A:$D,4,FALSE) -> 0.2 | E33: =($C$26*C33) -> 252
B34: HOTELARIAS | C34: =VLOOKUP($E$25&"-"&B34,Planilha2!$A:$D,4,FALSE) -> 0.1 | E34: =($C$26*C34) -> 126
E35: =SUM(E29:E34) -> 1323

Sheet Planilha2
A4: CHAVE COMPOSTA | B4: PERFIL | C4: TIPOS DE FI | D4: % | G4: ModeradoTIJOLO | H4: =VLOOKUP(G4,$A:$D,4,FALSE) -> #N/A
A5: =B5&"-"&C5 -> Conservador-PAPEL | B5: Conservador | C5: PAPEL | D5: 0.3
A6: =B6&"-"&C6 -> Conservador-TIJOLO | B6: Conservador | C6: TIJOLO | D6: 0.5
A7: =B7&"-"&C7 -> Conservador-HÍBRIDOS | B7: Conservador | C7: HÍBRIDOS | D7: 0.1
A8: =B8&"-"&C8 -> Conservador-FOFs | B8: Conservador | C8: FOFs | D8: 0.1
A9: =B9&"-"&C9 -> Conservador-DESENVOLVIMENTO | B9: Conservador | C9: DESENVOLVIMENTO | D9: 0
A10: =B10&"-"&C10 -> Conservador-HOTELARIAS | B10: Conservador | C10: HOTELARIAS | D10: 0
A11: =B11&"-"&C11 -> Moderado-PAPEL | B11: Moderado | C11: PAPEL | D11: 0.32
A12: =B12&"-"&C12 -> Moderado-TIJOLO | B12: Moderado | C12: TIJOLO | D12: 0.35
A13: =B13&"-"&C13 -> Moderado-HÍBRIDOS | B13: Moderado | C13: HÍBRIDOS | D13: 0.08
A14: =B14&"-"&C14 -> Moderado-FOFs | B14: Moderado | C14: FOFs | D14: 0.05
A15: =B15&"-"&C15 -> Moderado-DESENVOLVIMENTO | B15: Moderado | C15: DESENVOLVIMENTO | D15: 0.1
A16: =B16&"-"&C16 -> Moderado-HOTELARIAS | B16: Moderado | C16: HOTELARIAS | D16: 0.1
... A22: =B22&"-"&C22 -> Agressivo-HOTELARIAS | B22: Agressivo | C22: HOTELARIAS | D22: 0.1
